bakachon/__init__.py
bakachon/main.py
bakachon-1.0.0.2.dist-info/licenses/LICENSE.txt
bakachon-1.0.0.2.dist-info/METADATA
bakachon-1.0.0.2.dist-info/WHEEL
bakachon-1.0.0.2.dist-info/entry_points.txt
bakachon-1.0.0.2.dist-info/top_level.txt
bakachon-1.0.0.2.dist-info/RECORD
