Metadata-Version: 2.4
Name: bakachon
Version: 1.0.0.2
Summary: Take a Picture.
Author-email: Takayuki Kamiyama <karuma.reason@gmail.com>
License: The MIT License
Classifier: Programming Language :: Python :: 3.13
License-File: LICENSE.txt
Requires-Dist: cmake
Requires-Dist: opencv-python
Requires-Dist: opencv-contrib-python
Requires-Dist: pytk
Requires-Dist: Pillow
Dynamic: license-file
